{"specializari": {"TEOLOGIE PENTICOSTALA": 33, "MATEMATICA-INFORMATICA": 23}, "limba_moderna": {"LIMBA ENGLEZA": 56}, "limba_materna": {"LIMBA ROMANA": 56}, "promotie_anterioara": {"NU": 56}, "materii": {"LIMBA ROMANA": {"medie": 8.468750000000002, "reusita": 100.0, "cnt": 56}, "GENERAL": {"medie": 8.897023809523809, "reusita": 100.0, "cnt": 56}, "MATEMATICA MATE-INFO": {"medie": 9.295652173913044, "reusita": 100.0, "cnt": 23}, "INFORMATICA MI C/C++": {"medie": 9.475, "reusita": 100.0, "cnt": 4}, "GEOGRAFIE": {"medie": 8.646666666666667, "reusita": 100.0, "cnt": 30}, "ANATOMIE SI FIZIOLOGIE UMANA, GENETICA SI ECOLOGIE UMANA": {"medie": 9.290625000000002, "reusita": 100.0, "cnt": 16}, "ISTORIE": {"medie": 9.299999999999999, "reusita": 100.0, "cnt": 33}, "LOGICA, ARGUMENTARE SI COMUNICARE": {"medie": 8.950000000000001, "reusita": 100.0, "cnt": 3}, "CHIMIE ORGANICA TEO NIVEL I/II": {"medie": 8.983333333333333, "reusita": 100.0, "cnt": 3}}, "nume": "LICEUL TEOLOGIC PENTICOSTAL \"BETEL\" ORADEA\tBihor"}