{"specializari": {"TEHNICIAN ECOLOG SI PROTECTIA CALITATII MEDIULUI": 2, "TEHNICIAN MECANIC PENTRU INTRETINERE SI REPARATII": 8, "STIINTE SOCIALE": 1, "TEHNICIAN IN INDUSTRIA ALIMENTARA": 9}, "limba_moderna": {"LIMBA ENGLEZA": 19, "LIMBA FRANCEZA": 1}, "limba_materna": {"LIMBA ROMANA": 11, "LIMBA MAGHIARA": 9}, "promotie_anterioara": {"DA": 5, "NU": 15}, "materii": {"LIMBA ROMANA": {"medie": 3.496875, "reusita": 25.0, "cnt": 20}, "MATEMATICA TEHN": {"medie": 2.4166666666666665, "reusita": 15.789473684210526, "cnt": 19}, "BIOLOGIE VEGETALA SI ANIMALA": {"medie": 2.272222222222222, "reusita": 0.0, "cnt": 15}, "GENERAL": {"medie": 3.377884615384615, "reusita": 0.0, "cnt": 20}, "GEOGRAFIE": {"medie": 6.6, "reusita": 100.0, "cnt": 1}, "ANATOMIE SI FIZIOLOGIE UMANA, GENETICA SI ECOLOGIE UMANA": {"medie": 6.2, "reusita": 50.0, "cnt": 2}, "CHIMIE ANORGANICA TEH NIVEL I/II": {"medie": 3.5, "reusita": 50.0, "cnt": 2}, "ISTORIE": {"medie": 5.05, "reusita": 100.0, "cnt": 1}, "LIMBA MAGHIARA (REAL)": {"medie": 4.831250000000001, "reusita": 55.55555555555556, "cnt": 9}}, "nume": "LICEUL TEHNOLOGIC DUMBRAVIOARA\tMure\u0219"}