{"specializari": {"MATEMATICA-INFORMATICA": 1, "FILOLOGIE": 118, "STIINTE ALE NATURII": 27, "STIINTE SOCIALE": 28}, "limba_moderna": {"LIMBA ENGLEZA": 116, "LIMBA SPANIOLA": 19, "LIMBA FRANCEZA": 27, "LIMBA ITALIANA": 10, "LIMBA GERMANA MODERNA": 2}, "limba_materna": {"LIMBA ROMANA": 174}, "promotie_anterioara": {"DA": 1, "NU": 173}, "materii": {"LIMBA ROMANA": {"medie": 8.060632183908046, "reusita": 99.42528735632183, "cnt": 174}, "GENERAL": {"medie": 8.21120689655172, "reusita": 94.82758620689656, "cnt": 174}, "GEOGRAFIE": {"medie": 9.204687499999999, "reusita": 100.0, "cnt": 32}, "ANATOMIE SI FIZIOLOGIE UMANA, GENETICA SI ECOLOGIE UMANA": {"medie": 7.7681818181818185, "reusita": 100.0, "cnt": 22}, "MATEMATICA ST-NAT": {"medie": 7.412962962962964, "reusita": 96.29629629629629, "cnt": 27}, "MATEMATICA MATE-INFO": {"medie": 5.0, "reusita": 100.0, "cnt": 1}, "ISTORIE": {"medie": 7.973972602739725, "reusita": 99.31506849315068, "cnt": 146}, "LOGICA, ARGUMENTARE SI COMUNICARE": {"medie": 8.84896907216495, "reusita": 96.90721649484536, "cnt": 97}, "FIZICA TEO": {"medie": 6.9875, "reusita": 75.0, "cnt": 4}, "FILOSOFIE": {"medie": 9.35, "reusita": 100.0, "cnt": 1}, "PSIHOLOGIE": {"medie": 8.48, "reusita": 100.0, "cnt": 10}, "INFORMATICA SN C/C++": {"medie": 7.875, "reusita": 100.0, "cnt": 2}, "ECONOMIE": {"medie": 8.783333333333333, "reusita": 100.0, "cnt": 6}}, "nume": "LICEUL TEORETIC \"GEORGE CALINESCU\" CONSTANTA\tConstan\u021ba"}