{"specializari": {"MATEMATICA-INFORMATICA": 16, "FILOLOGIE": 52, "STIINTE ALE NATURII": 52, "STIINTE SOCIALE": 24}, "limba_moderna": {"LIMBA ENGLEZA": 144}, "limba_materna": {"LIMBA ROMANA": 96, "LIMBA MAGHIARA": 48}, "promotie_anterioara": {"NU": 137, "DA": 7}, "materii": {"LIMBA ROMANA": {"medie": 6.99027777777778, "reusita": 90.27777777777779, "cnt": 144}, "MATEMATICA MATE-INFO": {"medie": 6.249999999999998, "reusita": 75.0, "cnt": 16}, "BIOLOGIE VEGETALA SI ANIMALA": {"medie": 7.4125000000000005, "reusita": 100.0, "cnt": 8}, "GENERAL": {"medie": 7.1288483796296305, "reusita": 73.61111111111111, "cnt": 144}, "CHIMIE ORGANICA TEO NIVEL I/II": {"medie": 7.2, "reusita": 100.0, "cnt": 5}, "CHIMIE ANORGANICA TEO NIVEL I/II": {"medie": 8.825, "reusita": 100.0, "cnt": 4}, "ISTORIE": {"medie": 6.469736842105266, "reusita": 90.78947368421053, "cnt": 76}, "GEOGRAFIE": {"medie": 7.513541666666668, "reusita": 97.91666666666666, "cnt": 48}, "PSIHOLOGIE": {"medie": 7.05, "reusita": 100.0, "cnt": 2}, "MATEMATICA ST-NAT": {"medie": 6.883653846153846, "reusita": 86.53846153846155, "cnt": 52}, "ANATOMIE SI FIZIOLOGIE UMANA, GENETICA SI ECOLOGIE UMANA": {"medie": 7.7765306122448985, "reusita": 91.83673469387756, "cnt": 49}, "FIZICA TEO": {"medie": 7.875, "reusita": 100.0, "cnt": 2}, "LOGICA, ARGUMENTARE SI COMUNICARE": {"medie": 8.177272727272728, "reusita": 90.9090909090909, "cnt": 11}, "SOCIOLOGIE": {"medie": 6.27, "reusita": 73.33333333333333, "cnt": 15}, "LIMBA MAGHIARA (REAL)": {"medie": 7.648076923076924, "reusita": 100.0, "cnt": 26}, "LIMBA MAGHIARA (UMAN)": {"medie": 6.625, "reusita": 100.0, "cnt": 22}}, "nume": "LICEUL TEORETIC \"ANDREI BARSEANU\" TARNAVENI\tMure\u0219"}