{"specializari": {"TEHNICIAN IN ACTIVITATI ECONOMICE": 19, "FILOLOGIE": 22, "LICEU CU PROGRAM SPORTIV": 20, "TEHNICIAN DESENATOR PENTRU CONSTRUCTII SI INSTALATII": 1}, "limba_moderna": {"LIMBA ENGLEZA": 62}, "limba_materna": {"LIMBA ROMANA": 62}, "promotie_anterioara": {"NU": 44, "DA": 18}, "materii": {"LIMBA ROMANA": {"medie": 5.155833333333334, "reusita": 66.12903225806451, "cnt": 62}, "GENERAL": {"medie": 5.6847457627118665, "reusita": 32.25806451612903, "cnt": 62}, "ISTORIE": {"medie": 5.199999999999998, "reusita": 64.28571428571429, "cnt": 42}, "LOGICA, ARGUMENTARE SI COMUNICARE": {"medie": 2.8, "reusita": 0.0, "cnt": 2}, "SOCIOLOGIE": {"medie": 6.35, "reusita": 100.0, "cnt": 2}, "GEOGRAFIE": {"medie": 6.757142857142858, "reusita": 87.71929824561403, "cnt": 57}, "BIOLOGIE VEGETALA SI ANIMALA": {"medie": 1.5, "reusita": 0.0, "cnt": 1}, "MATEMATICA TEHN": {"medie": 5.413157894736843, "reusita": 65.0, "cnt": 20}}, "nume": "LICEUL TEHNOLOGIC \"NICOLAE BALCESCU\" VOLUNTARI\tIlfov"}