{"specializari": {"STIINTE ALE NATURII": 62, "FILOLOGIE": 67, "MATEMATICA-INFORMATICA": 19}, "limba_moderna": {"LIMBA ENGLEZA": 145, "LIMBA FRANCEZA": 3}, "limba_materna": {"LIMBA ROMANA": 148}, "promotie_anterioara": {"DA": 8, "NU": 140}, "materii": {"LIMBA ROMANA": {"medie": 7.2856164383561675, "reusita": 91.8918918918919, "cnt": 148}, "MATEMATICA ST-NAT": {"medie": 7.085483870967741, "reusita": 85.48387096774194, "cnt": 62}, "ANATOMIE SI FIZIOLOGIE UMANA, GENETICA SI ECOLOGIE UMANA": {"medie": 8.083088235294118, "reusita": 97.10144927536231, "cnt": 69}, "GENERAL": {"medie": 7.427011494252874, "reusita": 75.67567567567568, "cnt": 148}, "MATEMATICA MATE-INFO": {"medie": 5.586842105263158, "reusita": 68.42105263157895, "cnt": 19}, "ISTORIE": {"medie": 7.493846153846153, "reusita": 94.02985074626866, "cnt": 67}, "GEOGRAFIE": {"medie": 7.790517241379312, "reusita": 89.83050847457628, "cnt": 59}, "SOCIOLOGIE": {"medie": 6.487500000000001, "reusita": 60.0, "cnt": 5}, "FILOSOFIE": {"medie": 7.75, "reusita": 100.0, "cnt": 2}, "INFORMATICA MI PASCAL": {"medie": 6.964285714285715, "reusita": 85.71428571428571, "cnt": 7}, "CHIMIE ORGANICA TEO NIVEL I/II": {"medie": 9.03, "reusita": 100.0, "cnt": 5}, "ECONOMIE": {"medie": 8.25, "reusita": 100.0, "cnt": 1}}, "nume": "LICEUL TEORETIC \"AVRAM IANCU\" BRAD\tHunedoara"}