{"specializari": {"LICEU CU PROGRAM SPORTIV": 88, "MATEMATICA-INFORMATICA": 359, "TEHNICIAN ECOLOG SI PROTECTIA CALITATII MEDIULUI": 121, "FILOLOGIE": 385, "TEHNICIAN IN TURISM": 77, "TEHNICIAN DE TELECOMUNICATII": 52, "TEHNICIAN MECANIC PENTRU INTRETINERE SI REPARATII": 17, "TEHNICIAN MECATRONIST": 45, "STIINTE SOCIALE": 186, "TEHNICIAN ANALIZE PRODUSE ALIMENTARE": 23, "TEHNICIAN VETERINAR": 23, "STIINTE ALE NATURII": 262, "TEHNICIAN DESENATOR PENTRU CONSTRUCTII SI INSTALATII": 32, "TEHNICIAN PROIECTANT CAD": 21, "TEHNICIAN OPERATOR TEHNICA DE CALCUL": 41, "INVATATOR - EDUCATOARE": 23, "TEHNICIAN DESIGNER VESTIMENTAR": 34, "ORGANIZATOR BANQUETING": 38, "TEHNICIAN IN INDUSTRIA TEXTILA": 7, "TEHNICIAN ELECTROMECANIC": 40, "TEHNICIAN ELECTRONIST": 28, "TEHNICIAN HIDRO-METEOROLOG": 12, "TEHNICIAN TRANSPORTURI": 112, "TEHNICIAN ELECTRICIAN/ELECTRONIST AUTO": 41, "TEHNICIAN IN ACTIVITATI DE COMERT": 3, "TEHNICIAN IN ACTIVITATI ECONOMICE": 172, "TEHNICIAN IN INDUSTRIA ALIMENTARA": 22, "TEHNICIAN IN AUTOMATIZARI": 48, "TEHNICIAN OPERATOR PROCESARE TEXT IMAGINE": 8, "TEHNICIAN IN INSTALATII ELECTRICE": 21, "TEHNICIAN PRELUCRARI MECANICE": 11, "TEHNICIAN AGROMONTAN": 4, "TEHNICIAN IN HOTELARIE": 4, "TEHNICIAN ELECTROTEHNIST": 1, "MUZICA": 22, "TEHNICIAN IN ACHIZITII SI CONTRACTARI": 48, "TEHNICIAN IN GASTRONOMIE": 91, "ARTE PLASTICE SI DECORATIVE": 26, "TEHNICIAN IN ADMINISTRATIE": 29, "ARHITECTURA, ARTE AMBIENTALE SI DESIGN": 32, "TEHNICIAN PROIECTANT PRODUSE FINITE DIN LEMN": 5, "TEHNICIAN DESIGNER MOBILA SI AMENAJARI INTERIOARE": 8, "TEHNICIAN IN SILVICULTURA SI EXPLOATARI FORESTIERE": 2, "TEHNICIAN HORTICULTOR": 2}, "limba_moderna": {"LIMBA ENGLEZA": 2248, "LIMBA FRANCEZA": 333, "LIMBA GERMANA MODERNA": 3, "LIMBA SPANIOLA": 41, "LIMBA ITALIANA": 1}, "limba_materna": {"LIMBA ROMANA": 2626}, "promotie_anterioara": {"NU": 2112, "DA": 514}, "materii": {"LIMBA ROMANA": {"medie": 7.044076383476218, "reusita": 90.36557501904036, "cnt": 2626}, "MATEMATICA TEHN": {"medie": 6.281676495366472, "reusita": 73.61222847948513, "cnt": 1243}, "BIOLOGIE VEGETALA SI ANIMALA": {"medie": 5.630224403927066, "reusita": 63.37285902503294, "cnt": 759}, "GENERAL": {"medie": 7.135014678409404, "reusita": 67.8979436405179, "cnt": 2626}, "MATEMATICA ST-NAT": {"medie": 6.5965116279069775, "reusita": 79.00763358778626, "cnt": 262}, "CHIMIE ORGANICA TEO NIVEL I/II": {"medie": 8.991406250000002, "reusita": 100.0, "cnt": 64}, "ISTORIE": {"medie": 7.491369863013695, "reusita": 96.75236806495265, "cnt": 739}, "LOGICA, ARGUMENTARE SI COMUNICARE": {"medie": 8.832352941176467, "reusita": 100.0, "cnt": 34}, "MATEMATICA MATE-INFO": {"medie": 8.299582172701946, "reusita": 94.15041782729804, "cnt": 359}, "INFORMATICA MI C/C++": {"medie": 8.172826086956519, "reusita": 97.82608695652173, "cnt": 46}, "GEOGRAFIE": {"medie": 8.061044362292055, "reusita": 95.92391304347827, "cnt": 1104}, "ANATOMIE SI FIZIOLOGIE UMANA, GENETICA SI ECOLOGIE UMANA": {"medie": 7.17388888888889, "reusita": 87.02702702702703, "cnt": 185}, "FIZICA TEO": {"medie": 8.642410714285708, "reusita": 98.21428571428571, "cnt": 112}, "MATEMATICA PED": {"medie": 6.793478260869565, "reusita": 82.6086956521739, "cnt": 23}, "FIZICA TEH": {"medie": 6.316233766233762, "reusita": 86.07594936708861, "cnt": 79}, "SOCIOLOGIE": {"medie": 8.344999999999999, "reusita": 97.5, "cnt": 40}, "CHIMIE ANORGANICA TEO NIVEL I/II": {"medie": 7.641406249999999, "reusita": 96.875, "cnt": 64}, "PSIHOLOGIE": {"medie": 7.925000000000002, "reusita": 100.0, "cnt": 14}, "ECONOMIE": {"medie": 8.640000000000004, "reusita": 100.0, "cnt": 25}, "CHIMIE ANORGANICA TEH NIVEL I/II": {"medie": 5.8065476190476195, "reusita": 81.60919540229885, "cnt": 87}, "INFORMATICA MI PASCAL": {"medie": 7.9875, "reusita": 100.0, "cnt": 4}, "CHIMIE ORGANICA TEH NIVEL I/II": {"medie": 8.55, "reusita": 100.0, "cnt": 2}, "FILOSOFIE": {"medie": 8.35, "reusita": 100.0, "cnt": 7}}, "nume": "Vrancea"}