{"specializari": {"TEHNICIAN OPERATOR TEHNICA DE CALCUL": 53, "TEHNICIAN TRANSPORTURI": 43, "TEHNICIAN ELECTRICIAN/ELECTRONIST AUTO": 25, "TEHNICIAN IN GASTRONOMIE": 32, "TEHNICIAN ECOLOG SI PROTECTIA CALITATII MEDIULUI": 33, "TEHNICIAN IN ACHIZITII SI CONTRACTARI": 26, "TEHNICIAN CHIMIST DE LABORATOR": 5, "TEHNICIAN DESENATOR PENTRU CONSTRUCTII SI INSTALATII": 1}, "limba_moderna": {"LIMBA ENGLEZA": 171, "LIMBA FRANCEZA": 47}, "limba_materna": {"LIMBA ROMANA": 218}, "promotie_anterioara": {"NU": 173, "DA": 45}, "materii": {"LIMBA ROMANA": {"medie": 4.91831683168317, "reusita": 57.798165137614674, "cnt": 218}, "MATEMATICA TEHN": {"medie": 3.119900497512438, "reusita": 25.688073394495415, "cnt": 218}, "BIOLOGIE VEGETALA SI ANIMALA": {"medie": 3.416380952380952, "reusita": 22.58064516129032, "cnt": 124}, "GENERAL": {"medie": 4.294188481675392, "reusita": 16.055045871559635, "cnt": 218}, "GEOGRAFIE": {"medie": 6.35625, "reusita": 84.48275862068965, "cnt": 58}, "ANATOMIE SI FIZIOLOGIE UMANA, GENETICA SI ECOLOGIE UMANA": {"medie": 6.119696969696967, "reusita": 81.81818181818183, "cnt": 33}, "FIZICA TEH": {"medie": 5.625, "reusita": 66.66666666666666, "cnt": 3}}, "nume": "LICEUL TEHNOLOGIC \"GOGA IONESCU\" TITU\tD\u00e2mbovi\u021ba"}