{"specializari": {"TEHNICIAN MECANIC PENTRU INTRETINERE SI REPARATII": 3, "TEHNICIAN IN GASTRONOMIE": 9}, "limba_moderna": {"LIMBA ENGLEZA": 11, "LIMBA FRANCEZA": 1}, "limba_materna": {"LIMBA ROMANA": 12}, "promotie_anterioara": {"DA": 5, "NU": 7}, "materii": {"LIMBA ROMANA": {"medie": 5.695, "reusita": 66.66666666666666, "cnt": 12}, "MATEMATICA TEHN": {"medie": 3.6666666666666665, "reusita": 41.66666666666667, "cnt": 12}, "GENERAL": {"medie": 4.40625, "reusita": 8.333333333333332, "cnt": 12}, "GEOGRAFIE": {"medie": 5.1071428571428585, "reusita": 33.33333333333333, "cnt": 9}, "FIZICA TEH": {"medie": 2.05, "reusita": 0.0, "cnt": 3}}, "nume": "LICEUL TEHNOLOGIC \"DUILIU ZAMFIRESCU\" DRAGALINA\tC\u0103l\u0103ra\u0219i"}