{"specializari": {"TEOLOGIE ORTODOXA": 27}, "limba_moderna": {"LIMBA ENGLEZA": 27}, "limba_materna": {"LIMBA ROMANA": 27}, "promotie_anterioara": {"NU": 26, "DA": 1}, "materii": {"LIMBA ROMANA": {"medie": 7.684615384615385, "reusita": 96.29629629629629, "cnt": 27}, "GENERAL": {"medie": 7.875641025641025, "reusita": 92.5925925925926, "cnt": 27}, "ISTORIE": {"medie": 7.925000000000001, "reusita": 96.29629629629629, "cnt": 27}, "LOGICA, ARGUMENTARE SI COMUNICARE": {"medie": 8.266666666666667, "reusita": 100.0, "cnt": 3}, "GEOGRAFIE": {"medie": 7.984782608695654, "reusita": 95.83333333333334, "cnt": 24}}, "nume": "SEMINARUL TEOLOGIC ORTODOX \"SF.IOAN GURA DE AUR\" SLOBOZIA\tIalomi\u021ba"}