{"specializari": {"LICEU CU PROGRAM SPORTIV": 24, "STIINTE ALE NATURII": 28, "STIINTE SOCIALE": 28}, "limba_moderna": {"LIMBA ENGLEZA": 80}, "limba_materna": {"LIMBA ROMANA": 80}, "promotie_anterioara": {"DA": 4, "NU": 76}, "materii": {"LIMBA ROMANA": {"medie": 7.155128205128207, "reusita": 95.0, "cnt": 80}, "GENERAL": {"medie": 7.572077922077923, "reusita": 86.25, "cnt": 80}, "ANATOMIE SI FIZIOLOGIE UMANA, GENETICA SI ECOLOGIE UMANA": {"medie": 8.802083333333332, "reusita": 100.0, "cnt": 24}, "FIZICA TEO": {"medie": 9.7, "reusita": 100.0, "cnt": 1}, "GEOGRAFIE": {"medie": 7.299999999999999, "reusita": 100.0, "cnt": 34}, "ISTORIE": {"medie": 7.33529411764706, "reusita": 98.07692307692307, "cnt": 52}, "LOGICA, ARGUMENTARE SI COMUNICARE": {"medie": 7.6000000000000005, "reusita": 81.81818181818183, "cnt": 11}, "MATEMATICA ST-NAT": {"medie": 7.614285714285714, "reusita": 100.0, "cnt": 28}, "PSIHOLOGIE": {"medie": 7.825, "reusita": 100.0, "cnt": 2}, "CHIMIE ANORGANICA TEO NIVEL I/II": {"medie": 8.649999999999999, "reusita": 100.0, "cnt": 2}, "CHIMIE ORGANICA TEO NIVEL I/II": {"medie": 8.5, "reusita": 100.0, "cnt": 1}, "SOCIOLOGIE": {"medie": 8.76, "reusita": 100.0, "cnt": 5}}, "nume": "LICEUL TEORETIC \"LIVIU REBREANU\" TURDA\tCluj"}