{"specializari": {"TEHNICIAN IN MORARIT, PANIFICATIE SI PRODUSE FAINOASE": 7, "TEHNICIAN IN GASTRONOMIE": 15, "TEHNICIAN MECATRONIST": 1, "TEHNICIAN ANALIZE PRODUSE ALIMENTARE": 8, "TEHNICIAN IN INDUSTRIA ALIMENTARA": 2, "TEHNICIAN ELECTROMECANIC": 1}, "limba_moderna": {"LIMBA ENGLEZA": 33, "LIMBA FRANCEZA": 1}, "limba_materna": {"LIMBA ROMANA": 34}, "promotie_anterioara": {"NU": 25, "DA": 9}, "materii": {"LIMBA ROMANA": {"medie": 4.943548387096774, "reusita": 55.88235294117647, "cnt": 34}, "GEOGRAFIE": {"medie": 6.25, "reusita": 71.42857142857143, "cnt": 14}, "GENERAL": {"medie": 4.524358974358974, "reusita": 8.823529411764707, "cnt": 34}, "ANATOMIE SI FIZIOLOGIE UMANA, GENETICA SI ECOLOGIE UMANA": {"medie": 3.5269230769230777, "reusita": 14.285714285714285, "cnt": 14}, "BIOLOGIE VEGETALA SI ANIMALA": {"medie": 5.32, "reusita": 60.0, "cnt": 5}, "MATEMATICA TEHN": {"medie": 3.4888888888888885, "reusita": 23.52941176470588, "cnt": 34}, "LOGICA, ARGUMENTARE SI COMUNICARE": {"medie": 8.5, "reusita": 100.0, "cnt": 1}}, "nume": "LICEUL DE INDUSTRIE ALIMENTARA CRAIOVA\tDolj"}