{"specializari": {"TEHNICIAN IN SILVICULTURA SI EXPLOATARI FORESTIERE": 50, "TEHNICIAN ECOLOG SI PROTECTIA CALITATII MEDIULUI": 2, "TEHNICIAN IN PRELUCRAREA LEMNULUI": 1, "TEHNICIAN MECATRONIST": 1}, "limba_moderna": {"LIMBA ENGLEZA": 40, "LIMBA FRANCEZA": 14}, "limba_materna": {"LIMBA ROMANA": 54}, "promotie_anterioara": {"NU": 37, "DA": 17}, "materii": {"LIMBA ROMANA": {"medie": 6.199038461538463, "reusita": 85.18518518518519, "cnt": 54}, "GENERAL": {"medie": 5.637666666666666, "reusita": 29.629629629629626, "cnt": 54}, "ANATOMIE SI FIZIOLOGIE UMANA, GENETICA SI ECOLOGIE UMANA": {"medie": 6.5, "reusita": 50.0, "cnt": 4}, "BIOLOGIE VEGETALA SI ANIMALA": {"medie": 5.508163265306122, "reusita": 68.0, "cnt": 50}, "MATEMATICA TEHN": {"medie": 5.045370370370372, "reusita": 68.51851851851852, "cnt": 54}}, "nume": "LICEUL SILVIC GURGHIU\tMure\u0219"}