{"specializari": {"STIINTE ALE NATURII": 21, "MATEMATICA-INFORMATICA": 1}, "limba_moderna": {"LIMBA ENGLEZA": 22}, "limba_materna": {"LIMBA ROMANA": 22}, "promotie_anterioara": {"NU": 17, "DA": 5}, "materii": {"LIMBA ROMANA": {"medie": 6.754545454545456, "reusita": 81.81818181818183, "cnt": 22}, "GENERAL": {"medie": 6.222222222222221, "reusita": 45.45454545454545, "cnt": 22}, "MATEMATICA ST-NAT": {"medie": 4.2785714285714285, "reusita": 52.38095238095239, "cnt": 21}, "ANATOMIE SI FIZIOLOGIE UMANA, GENETICA SI ECOLOGIE UMANA": {"medie": 7.616666666666667, "reusita": 86.36363636363636, "cnt": 22}, "MATEMATICA MATE-INFO": {"medie": 5.0, "reusita": 100.0, "cnt": 1}}, "nume": "LICEUL TEORETIC \"GELU VOIEVOD\" GILAU\tCluj"}