{"specializari": {"TEHNICIAN IN ACTIVITATI ECONOMICE": 50, "TEHNICIAN OPERATOR TEHNICA DE CALCUL": 37, "TEHNICIAN TRANSPORTURI": 32, "TEHNICIAN IN TURISM": 3, "TEHNICIAN ELECTRICIAN/ELECTRONIST AUTO": 3, "TEHNICIAN ANALIZE PRODUSE ALIMENTARE": 3, "TEHNICIAN IN INDUSTRIA ALIMENTARA": 2, "TEHNICIAN IN INSTALATII ELECTRICE": 1, "TEHNICIAN IN CONSTRUCTII SI LUCRARI PUBLICE": 1}, "limba_moderna": {"LIMBA ENGLEZA": 131, "LIMBA FRANCEZA": 1}, "limba_materna": {"LIMBA ROMANA": 132}, "promotie_anterioara": {"NU": 72, "DA": 60}, "materii": {"LIMBA ROMANA": {"medie": 5.35614035087719, "reusita": 64.39393939393939, "cnt": 132}, "MATEMATICA TEHN": {"medie": 3.4458715596330283, "reusita": 30.303030303030305, "cnt": 132}, "BIOLOGIE VEGETALA SI ANIMALA": {"medie": 4.552985074626866, "reusita": 41.66666666666667, "cnt": 72}, "GENERAL": {"medie": 4.753301886792454, "reusita": 22.727272727272727, "cnt": 132}, "FIZICA TEH": {"medie": 2.925, "reusita": 14.285714285714285, "cnt": 7}, "GEOGRAFIE": {"medie": 7.179166666666668, "reusita": 62.264150943396224, "cnt": 53}}, "nume": "LICEUL TEHNOLOGIC \"UNIREA\" STEI\tBihor"}