{"specializari": {"STIINTE SOCIALE": 9}, "limba_moderna": {"LIMBA ENGLEZA": 9}, "limba_materna": {"LIMBA ROMANA": 9}, "promotie_anterioara": {"NU": 5, "DA": 4}, "materii": {"LIMBA ROMANA": {"medie": 5.749999999999999, "reusita": 88.88888888888889, "cnt": 9}, "GENERAL": {"medie": 6.992592592592593, "reusita": 77.77777777777779, "cnt": 9}, "ISTORIE": {"medie": 7.794444444444445, "reusita": 100.0, "cnt": 9}, "GEOGRAFIE": {"medie": 7.4125000000000005, "reusita": 100.0, "cnt": 4}, "LOGICA, ARGUMENTARE SI COMUNICARE": {"medie": 7.766666666666667, "reusita": 100.0, "cnt": 3}, "SOCIOLOGIE": {"medie": 6.975, "reusita": 100.0, "cnt": 2}}, "nume": "LICEUL TEORETIC \"PONTUS EUXINUS\" LUMINA\tConstan\u021ba"}