{"specializari": {"MATEMATICA-INFORMATICA": 170}, "limba_moderna": {"LIMBA ENGLEZA": 169, "LIMBA GERMANA MODERNA": 1}, "limba_materna": {"LIMBA ROMANA": 170}, "promotie_anterioara": {"NU": 169, "DA": 1}, "materii": {"LIMBA ROMANA": {"medie": 8.426176470588235, "reusita": 100.0, "cnt": 170}, "MATEMATICA MATE-INFO": {"medie": 8.905882352941177, "reusita": 100.0, "cnt": 170}, "INFORMATICA MI C/C++": {"medie": 8.890650406504067, "reusita": 100.0, "cnt": 123}, "GENERAL": {"medie": 8.722647058823526, "reusita": 98.82352941176471, "cnt": 170}, "CHIMIE ORGANICA TEO NIVEL I/II": {"medie": 9.5125, "reusita": 100.0, "cnt": 4}, "FIZICA TEO": {"medie": 9.61, "reusita": 100.0, "cnt": 5}, "ANATOMIE SI FIZIOLOGIE UMANA, GENETICA SI ECOLOGIE UMANA": {"medie": 8.455555555555556, "reusita": 97.22222222222221, "cnt": 36}, "CHIMIE ANORGANICA TEO NIVEL I/II": {"medie": 9.025, "reusita": 100.0, "cnt": 2}}, "nume": "LICEUL TEORETIC DE INFORMATICA \"GRIGORE MOISIL\", IASI\tIa\u0219i"}