{"specializari": {"STIINTE ALE NATURII": 39, "FILOLOGIE": 57}, "limba_moderna": {"LIMBA ENGLEZA": 90, "LIMBA GERMANA MODERNA": 6}, "limba_materna": {"LIMBA GERMANA": 38, "LIMBA ROMANA": 58}, "promotie_anterioara": {"NU": 92, "DA": 4}, "materii": {"LIMBA ROMANA": {"medie": 7.0828125, "reusita": 96.875, "cnt": 96}, "GENERAL": {"medie": 7.204123263888885, "reusita": 83.33333333333334, "cnt": 96}, "ISTORIE": {"medie": 7.1842105263157885, "reusita": 98.24561403508771, "cnt": 57}, "LOGICA, ARGUMENTARE SI COMUNICARE": {"medie": 6.891666666666667, "reusita": 66.66666666666666, "cnt": 6}, "GEOGRAFIE": {"medie": 8.210606060606064, "reusita": 100.0, "cnt": 33}, "MATEMATICA ST-NAT": {"medie": 6.992307692307693, "reusita": 94.87179487179486, "cnt": 39}, "SOCIOLOGIE": {"medie": 7.079411764705883, "reusita": 94.11764705882352, "cnt": 17}, "ANATOMIE SI FIZIOLOGIE UMANA, GENETICA SI ECOLOGIE UMANA": {"medie": 7.093103448275863, "reusita": 93.10344827586206, "cnt": 29}, "CHIMIE ANORGANICA TEO NIVEL I/II": {"medie": 8.575, "reusita": 100.0, "cnt": 10}, "FILOSOFIE": {"medie": 10.0, "reusita": 100.0, "cnt": 1}, "LIMBA GERMANA": {"medie": 7.1000000000000005, "reusita": 92.10526315789474, "cnt": 38}}, "nume": "LICEUL TEORETIC \"ADAM MULLER GUTTENBRUNN\" ARAD\tArad"}