{"specializari": {"FILOLOGIE": 31, "TEHNICIAN IN ACTIVITATI ECONOMICE": 2, "TEHNICIAN IN TURISM": 2}, "limba_moderna": {"LIMBA ENGLEZA": 35}, "limba_materna": {"LIMBA ROMANA": 35}, "promotie_anterioara": {"NU": 17, "DA": 18}, "materii": {"LIMBA ROMANA": {"medie": 5.616176470588236, "reusita": 82.85714285714286, "cnt": 35}, "GENERAL": {"medie": 6.058854166666666, "reusita": 48.57142857142857, "cnt": 35}, "ISTORIE": {"medie": 6.103448275862068, "reusita": 80.64516129032258, "cnt": 31}, "LOGICA, ARGUMENTARE SI COMUNICARE": {"medie": 4.887499999999999, "reusita": 40.0, "cnt": 5}, "GEOGRAFIE": {"medie": 7.005357142857141, "reusita": 89.65517241379311, "cnt": 29}, "PSIHOLOGIE": {"medie": "-", "reusita": 0.0, "cnt": 1}, "MATEMATICA TEHN": {"medie": 3.675, "reusita": 50.0, "cnt": 4}}, "nume": "LICEUL TEHNOLOGIC \"VIRGIL MADGEARU\" CLUJ-NAPOCA\tCluj"}