{"specializari": {"LICEU CU PROGRAM SPORTIV": 78}, "limba_moderna": {"LIMBA ENGLEZA": 78}, "limba_materna": {"LIMBA ROMANA": 78}, "promotie_anterioara": {"NU": 57, "DA": 21}, "materii": {"LIMBA ROMANA": {"medie": 5.640131578947371, "reusita": 78.2051282051282, "cnt": 78}, "GENERAL": {"medie": 6.002777777777777, "reusita": 48.717948717948715, "cnt": 78}, "ISTORIE": {"medie": 5.3298611111111125, "reusita": 67.94871794871796, "cnt": 78}, "LOGICA, ARGUMENTARE SI COMUNICARE": {"medie": 5.875, "reusita": 62.5, "cnt": 8}, "GEOGRAFIE": {"medie": 7.1795454545454565, "reusita": 95.58823529411765, "cnt": 68}, "PSIHOLOGIE": {"medie": 5.45, "reusita": 100.0, "cnt": 2}}, "nume": "LICEUL CU PROGRAM SPORTIV ARAD\tArad"}